{"date": "2024-11-14", "location": "Berkshire", "id": "11/14/2024-4", "meals": [{"meal": "grabngo", "category": "Grab n'Go Breakfast", "food": "Breakfast Burrito"}, {"meal": "grabngo", "category": "Grab n'Go Breakfast", "food": "Butter Croissant"}, {"meal": "grabngo", "category": "Grab n'Go Breakfast", "food": "Corned Beef Hash"}, {"meal": "grabngo", "category": "Grab n'Go Breakfast", "food": "GF Bacon Breakfast Bagel Sandwich"}, {"meal": "grabngo", "category": "Grab n'Go Breakfast", "food": "GF Breakfast Bagel Sandwich"}, {"meal": "grabngo", "category": "Grab n'Go Breakfast", "food": "Gingerbread Scuffin"}, {"meal": "grabngo", "category": "Grab n'Go Breakfast", "food": "Hot Oatmeal"}, {"meal": "grabngo", "category": "Grab n'Go Breakfast", "food": "O'Brien Potatoes"}, {"meal": "grabngo", "category": "Grab n'Go Breakfast", "food": "Sausage Breakfast Burrito"}, {"meal": "grabngo", "category": "Grab n'Go Breakfast", "food": "Scrambled Eggs"}, {"meal": "grabngo", "category": "Grab n'Go Breakfast", "food": "Strawberry Yogurt Parfait"}, {"meal": "grabngo", "category": "Grab n'Go Hot ", "food": "Double Chocolate Chip Cookies"}, {"meal": "grabngo", "category": "Grab n'Go Hot ", "food": "French Fries"}, {"meal": "grabngo", "category": "Grab n'Go Hot ", "food": "Lemon Blondie"}, {"meal": "grabngo", "category": "Grab n'Go Hot ", "food": "Mashed Potatoes"}, {"meal": "grabngo", "category": "Grab n'Go Hot ", "food": "Penne w/Basil Pesto Cream & Sun Dried Tomatoes"}, {"meal": "grabngo", "category": "Grab n'Go Hot ", "food": "Philly Cheese Steak Grinder"}, {"meal": "grabngo", "category": "Grab n'Go Hot ", "food": "Roast Turkey"}, {"meal": "grabngo", "category": "Grab n'Go Hot ", "food": "Roasted Butternut Squash"}, {"meal": "grabngo", "category": "Grab n'Go Hot ", "food": "Turkey Gravy"}, {"meal": "grabngo", "category": "Grab n'Go Cold ", "food": "Buffalo Chicken Wrap"}, {"meal": "grabngo", "category": "Grab n'Go Cold ", "food": "Chicken Caesar Salad"}, {"meal": "grabngo", "category": "Grab n'Go Cold ", "food": "Fruit Salad"}, {"meal": "grabngo", "category": "Grab n'Go Cold ", "food": "GF Peanut Butter & Strawberry Jam Sandwich"}, {"meal": "grabngo", "category": "Grab n'Go Cold ", "food": "Gluten Free Turkey Sandwich"}, {"meal": "grabngo", "category": "Grab n'Go Cold ", "food": "Tossed Salad"}, {"meal": "grabngo", "category": "Grab n'Go Cold ", "food": "Tuna on White"}, {"meal": "lunch", "category": "Soups", "food": "Lasagna Soup w/Turkey Sausage"}, {"meal": "lunch", "category": "Soups", "food": "Organic Black Bean Soup"}, {"meal": "lunch", "category": "Entrees", "food": "Ellis Family Herbed Chicken"}, {"meal": "lunch", "category": "Starches", "food": "BUSH's Baked Beans"}, {"meal": "lunch", "category": "Starches", "food": "Lyonnaise Potatoes"}, {"meal": "lunch", "category": "Starches", "food": "Spiced Cauliflower & Chickpeas"}, {"meal": "lunch", "category": "Vegetables", "food": "Honey Glazed Carrots & Parsnips"}, {"meal": "lunch", "category": "Vegetables", "food": "Saut\u00e9ed Kale"}, {"meal": "lunch", "category": "Grill Station", "food": "Grilled Chicken Breast"}, {"meal": "lunch", "category": "Grill Station", "food": "Grilled Chicken Thighs"}, {"meal": "lunch", "category": "Grill Station", "food": "Halal Burger Patty"}, {"meal": "lunch", "category": "Grill Station", "food": "Halal French Fries"}, {"meal": "lunch", "category": "Grill Station", "food": "Hand Cut Sweet Potato Fries"}, {"meal": "lunch", "category": "Grill Station", "food": "Kelp Burger"}, {"meal": "lunch", "category": "International ", "food": "Green Curry Thai Pulmuone Tofu"}, {"meal": "lunch", "category": "International ", "food": "Honey Lemongrass Chicken"}, {"meal": "lunch", "category": "International ", "food": "Pad Thai w/Peanuts"}, {"meal": "lunch", "category": "International ", "food": "Stir Fry Green Vegetables"}, {"meal": "lunch", "category": "International ", "food": "Vegetable Fried Rice"}, {"meal": "lunch", "category": "International ", "food": "Vegetable Spring Rolls"}, {"meal": "lunch", "category": "Pasta Bar", "food": "Cheese Rigatoni w/Plant Based Nasoya Bolognese Sauce"}, {"meal": "lunch", "category": "Pasta Bar", "food": "Linguini Pasta"}, {"meal": "lunch", "category": "Pasta Bar", "food": "Marinara Sauce"}, {"meal": "lunch", "category": "Pasta Bar", "food": "Penne Pasta"}, {"meal": "lunch", "category": "Pasta Bar", "food": "Plant Based Bolognese Sauce"}, {"meal": "lunch", "category": "Deli Bar", "food": "American Cheese"}, {"meal": "lunch", "category": "Deli Bar", "food": "Chicken Salad"}, {"meal": "lunch", "category": "Deli Bar", "food": "Deli Beef"}, {"meal": "lunch", "category": "Deli Bar", "food": "Homemade Mid Eastern Hummus"}, {"meal": "lunch", "category": "Deli Bar", "food": "Provolone Cheese"}, {"meal": "lunch", "category": "Deli Bar", "food": "Tuna Salad"}, {"meal": "lunch", "category": "Deli Bar", "food": "Turkey Breast"}, {"meal": "lunch", "category": "Desserts", "food": "Chocolate Drop Cookies"}, {"meal": "lunch", "category": "Desserts", "food": "Rice Krispy Treats"}, {"meal": "lunch", "category": "Noodle Bowl", "food": "Bun Heo Quay (Crispy Pork Belly Bowl)"}, {"meal": "lunch", "category": "Noodle Bowl", "food": "Pickled Daikon & Carrots"}, {"meal": "lunch", "category": "Noodle Bowl", "food": "Roasted Crispy Pork Belly"}, {"meal": "lunch", "category": "Noodle Bowl", "food": "Sweet Chili Sauce"}, {"meal": "lunch", "category": "Noodle Bowl", "food": "Vietnamese Nam Nem Sauce"}, {"meal": "lunch", "category": "Pizza", "food": "Cheese Pizza"}, {"meal": "lunch", "category": "Pizza", "food": "Pepperoni Pizza"}, {"meal": "lunch", "category": "Display Station", "food": "8\" Flour Tortilla"}, {"meal": "lunch", "category": "Display Station", "food": "Beef Fajita (Meat Only)"}, {"meal": "lunch", "category": "Display Station", "food": "Corn and Red Peppers"}, {"meal": "lunch", "category": "Display Station", "food": "Latin Toppings"}, {"meal": "lunch", "category": "Display Station", "food": "Red Beans"}, {"meal": "lunch", "category": "Display Station", "food": "Yellow Rice"}, {"meal": "dinner", "category": "Soups", "food": "Lasagna Soup w/Turkey Sausage"}, {"meal": "dinner", "category": "Soups", "food": "Organic Black Bean Soup"}, {"meal": "dinner", "category": "Entrees", "food": "Creamy Tuscan Salmon"}, {"meal": "dinner", "category": "Entrees", "food": "Orecchiette w/Sausage, Broccolini & Tomatoes"}, {"meal": "dinner", "category": "Starches", "food": "Garlic Bread"}, {"meal": "dinner", "category": "Starches", "food": "Polenta Florentine"}, {"meal": "dinner", "category": "Vegetables", "food": "Italian Summer Vegetables"}, {"meal": "dinner", "category": "Vegetables", "food": "Margherita Eggplant w/Pesto"}, {"meal": "dinner", "category": "Vegetables", "food": "Marinated Tomato & Mozzarella Salad"}, {"meal": "dinner", "category": "Grill Station", "food": "Grilled Chicken Breast"}, {"meal": "dinner", "category": "Grill Station", "food": "Grilled Chicken Thighs"}, {"meal": "dinner", "category": "Grill Station", "food": "Halal Burger Patty"}, {"meal": "dinner", "category": "Grill Station", "food": "Halal French Fries"}, {"meal": "dinner", "category": "Grill Station", "food": "Hand Cut Sweet Potato Fries"}, {"meal": "dinner", "category": "Grill Station", "food": "Kelp Burger"}, {"meal": "dinner", "category": "International ", "food": "Egg & Tomato Stir Fry"}, {"meal": "dinner", "category": "International ", "food": "Korean BBQ Chicken"}, {"meal": "dinner", "category": "International ", "food": "Korean Fried Rice w/Nasyoa Kimchi"}, {"meal": "dinner", "category": "International ", "food": "Pulmuone Tofu w/Ssamjang Sauce"}, {"meal": "dinner", "category": "International ", "food": "Stir Fry Green Vegetables"}, {"meal": "dinner", "category": "International ", "food": "Vegetable Spring Rolls"}, {"meal": "dinner", "category": "Pasta Bar", "food": "Linguini Pasta"}, {"meal": "dinner", "category": "Pasta Bar", "food": "Marinara Sauce"}, {"meal": "dinner", "category": "Pasta Bar", "food": "Penne Pasta"}, {"meal": "dinner", "category": "Pasta Bar", "food": "Tomato Cream Basil Sauce"}, {"meal": "dinner", "category": "Pasta Bar", "food": "Tortellini w/Basil Pesto & Grape Tomatoes"}, {"meal": "dinner", "category": "Salad Bar/Dressings", "food": "Alfalfa Sprouts"}, {"meal": "dinner", "category": "Salad Bar/Dressings", "food": "Banana Peppers"}, {"meal": "dinner", "category": "Salad Bar/Dressings", "food": "Cannellini Bean Salad w/Red Onion & Olives"}, {"meal": "dinner", "category": "Salad Bar/Dressings", "food": "Carrots Sticks"}, {"meal": "dinner", "category": "Salad Bar/Dressings", "food": "Celery Sticks"}, {"meal": "dinner", "category": "Salad Bar/Dressings", "food": "Chickpeas"}, {"meal": "dinner", "category": "Salad Bar/Dressings", "food": "Chopped Walnuts"}, {"meal": "dinner", "category": "Salad Bar/Dressings", "food": "Craisins"}, {"meal": "dinner", "category": "Salad Bar/Dressings", "food": "Cucumbers"}, {"meal": "dinner", "category": "Salad Bar/Dressings", "food": "Feta Cheese"}, {"meal": "dinner", "category": "Salad Bar/Dressings", "food": "Grape Tomatoes"}, {"meal": "dinner", "category": "Salad Bar/Dressings", "food": "Green Olives"}, {"meal": "dinner", "category": "Salad Bar/Dressings", "food": "Green Peppers"}, {"meal": "dinner", "category": "Salad Bar/Dressings", "food": "Homemade Mid Eastern Hummus"}, {"meal": "dinner", "category": "Salad Bar/Dressings", "food": "Kale & Carrot Salad w/ Pepitas & Tahini"}, {"meal": "dinner", "category": "Salad Bar/Dressings", "food": "Marinated Olives, Tomatoes & Artichokes"}, {"meal": "dinner", "category": "Salad Bar/Dressings", "food": "Olive Tapenade"}, {"meal": "dinner", "category": "Salad Bar/Dressings", "food": "Onions"}, {"meal": "dinner", "category": "Salad Bar/Dressings", "food": "Parmesan Cheese"}, {"meal": "dinner", "category": "Salad Bar/Dressings", "food": "Pita Chips"}, {"meal": "dinner", "category": "Salad Bar/Dressings", "food": "Pulmuone Tofu"}, {"meal": "dinner", "category": "Salad Bar/Dressings", "food": "Radishes"}, {"meal": "dinner", "category": "Salad Bar/Dressings", "food": "Romaine Lettuce"}, {"meal": "dinner", "category": "Salad Bar/Dressings", "food": "Sliced Eggs"}, {"meal": "dinner", "category": "Salad Bar/Dressings", "food": "Sliced Mushrooms"}, {"meal": "dinner", "category": "Salad Bar/Dressings", "food": "Spinach Leaves"}, {"meal": "dinner", "category": "Salad Bar/Dressings", "food": "Sunflower Seeds"}, {"meal": "dinner", "category": "Salad Bar/Dressings", "food": "Tuna"}, {"meal": "dinner", "category": "Desserts", "food": "Banana Choc Chip Cake"}, {"meal": "dinner", "category": "Desserts", "food": "Sweet Red Bean Cheesecake"}, {"meal": "dinner", "category": "Breads", "food": "Hawaiian Roll"}, {"meal": "dinner", "category": "Noodle Bowl", "food": "Halal Pho Noodle Bowl"}, {"meal": "dinner", "category": "Pizza", "food": "Cheese Pizza"}, {"meal": "dinner", "category": "Pizza", "food": "Pepperoni Pizza"}, {"meal": "dinner", "category": "Sushi", "food": "California Roll"}, {"meal": "dinner", "category": "Sushi", "food": "California Roll with Brown Rice"}, {"meal": "dinner", "category": "Sushi", "food": "Salmon Sushi Roll"}, {"meal": "dinner", "category": "Sushi", "food": "Shrimp Sushi Roll"}, {"meal": "dinner", "category": "Sushi", "food": "Vegetable Sushi Roll"}, {"meal": "dinner", "category": "Sushi", "food": "Vegetable Sushi Roll w/Brown Rice"}, {"meal": "dinner", "category": "Sushi", "food": "Vegetarian Brown Sushi Roll"}, {"meal": "dinner", "category": "Display Station", "food": "Ancho Lime Pulled Chicken"}, {"meal": "dinner", "category": "Display Station", "food": "Corn Tostada"}, {"meal": "dinner", "category": "Display Station", "food": "Pickled Red Onions"}, {"meal": "dinner", "category": "Display Station", "food": "Plant Based Chorizo Crumbles"}, {"meal": "dinner", "category": "Display Station", "food": "Queso Fresco"}, {"meal": "dinner", "category": "Display Station", "food": "Refried Black Beans"}, {"meal": "dinner", "category": "Display Station", "food": "Salsa Verde con Aguacate"}, {"meal": "dinner", "category": "Display Station", "food": "Sour Cream"}, {"meal": "dinner", "category": "Display Station", "food": "Yellow Rice"}, {"meal": "late night", "category": "Breakfast Entrees", "food": "Canadian Bacon"}, {"meal": "late night", "category": "Breakfast Entrees", "food": "Fried Plantain"}, {"meal": "late night", "category": "Breakfast Entrees", "food": "Mexican Migas (Tortilla Scrambled Eggs)"}, {"meal": "late night", "category": "Breakfast Entrees", "food": "Roasted Tomatoes"}, {"meal": "late night", "category": "Entrees", "food": "Italian Vegetables & White Beans"}, {"meal": "late night", "category": "Entrees", "food": "Rice Pilaf"}, {"meal": "late night", "category": "Entrees", "food": "Roasted Butternut Squash w/Spices"}, {"meal": "late night", "category": "Entrees", "food": "Shake & Bake Chicken Legs"}, {"meal": "late night", "category": "Entrees", "food": "Spinach w/Mushrooms"}, {"meal": "late night", "category": "Entrees", "food": "Vegetable Lasagna"}, {"meal": "late night", "category": "Desserts", "food": "OATLY Chocolate Soft Serve"}, {"meal": "late night", "category": "Desserts", "food": "OATLY Vanilla Soft Serve"}, {"meal": "late night", "category": "Pizza", "food": "Cheese Pizza"}, {"meal": "late night", "category": "Pizza", "food": "Pepperoni Pizza"}, {"meal": "late night", "category": "Pizza", "food": "Vegetable Pizza"}, {"meal": "late night", "category": "Display Station", "food": "Pearl Sugar Waffle Sundae"}]}